pvgridder/__about__.py
pvgridder/__init__.py
pvgridder/core/__init__.py
pvgridder/core/_base.py
pvgridder/core/_helpers.py
pvgridder/core/extrude.py
pvgridder/core/geometric_objects.py
pvgridder/core/merge.py
pvgridder/core/stack.py
pvgridder/core/voronoi.py
pvgridder/examples/__init__.py
pvgridder/examples/examples.py
pvgridder/utils/__init__.py
pvgridder/utils/_connectivity.py
pvgridder/utils/_interactive.py
pvgridder/utils/_misc.py
pvgridder/utils/_properties.py
pyvista_gridder-0.5.3.dist-info/licenses/LICENSE
pyvista_gridder-0.5.3.dist-info/METADATA
pyvista_gridder-0.5.3.dist-info/WHEEL
pyvista_gridder-0.5.3.dist-info/top_level.txt
pyvista_gridder-0.5.3.dist-info/RECORD
