Metadata-Version: 2.4
Name: pyvista-gridder
Version: 0.5.3
Summary: Mesh generation using PyVista
Author-email: Keurfon Luu <kluu@intera.com>
License-Expression: BSD-3-Clause
Project-URL: Homepage, https://github.com/INTERA-Inc/pyvista-gridder
Project-URL: Code, https://github.com/INTERA-Inc/pyvista-gridder
Project-URL: Issues, https://github.com/INTERA-Inc/pyvista-gridder/issues
Keywords: mesh generation,numerical modeling,pyvista
Classifier: Operating System :: OS Independent
Classifier: Development Status :: 4 - Beta
Classifier: Programming Language :: Python :: 3.9
Classifier: Programming Language :: Python :: 3.10
Classifier: Programming Language :: Python :: 3.11
Classifier: Programming Language :: Python :: 3.12
Classifier: Programming Language :: Python :: 3.13
Classifier: Natural Language :: English
Classifier: Intended Audience :: Science/Research
Classifier: Topic :: Scientific/Engineering
Requires-Python: >=3.9
License-File: LICENSE
Requires-Dist: numpy>=1.13.0
Requires-Dist: pyrequire>=0.2.0
Requires-Dist: pyvista>=0.45
Requires-Dist: scipy>=0.9
Requires-Dist: vtk>=9.4
Provides-Extra: full
Requires-Dist: gmsh; extra == "full"
Requires-Dist: shapely>=2.0; extra == "full"
Dynamic: license-file
